atlas/__init__.py
atlas/atlas.py
atlas/boundary.py
atlas/db.py
atlas/schema.py
dabbas/__init__.py
dabbas/cache.py
dabbas/connection.py
dabbas/db.py
dabbas/main.py
dabbas/map.py
dabbas-0.1.23.dist-info/METADATA
dabbas-0.1.23.dist-info/WHEEL
dabbas-0.1.23.dist-info/entry_points.txt
dabbas-0.1.23.dist-info/top_level.txt
dabbas-0.1.23.dist-info/RECORD
