Metadata-Version: 2.1
Name: dabbas
Version: 0.1.23
Classifier: Development Status :: 3 - Alpha
Classifier: License :: OSI Approved :: MIT License
Classifier: Programming Language :: Python :: 3
Classifier: Programming Language :: Python :: 3.6
Classifier: Programming Language :: Python :: 3.7
Classifier: Programming Language :: Python :: 3.8
Classifier: Programming Language :: Python :: 3.9
Requires-Dist: pandas-flavor
Requires-Dist: SQLAlchemy
Requires-Dist: pandas
Requires-Dist: geopandas
Requires-Dist: psycopg2-binary
Requires-Dist: shapely
Requires-Dist: folium
Requires-Dist: strawberry-graphql
Requires-Dist: supabase
